constava/__init__.py
constava/__main__.py
constava/calc/__init__.py
constava/calc/calculator.py
constava/calc/csmodels.py
constava/calc/subsampling.py
constava/data/constava_csdata.json
constava/data/constava_testdata.tgz
constava/io/__init__.py
constava/io/reader.py
constava/io/rstrategies.py
constava/io/writer.py
constava/io/wstrategies.py
constava/tests/__init__.py
constava/tests/tests.py
constava/utils/__init__.py
constava/utils/constants.py
constava/utils/dihedrals.py
constava/utils/ensembles.py
constava/utils/logging.py
constava/utils/results.py
constava/utils/utils.py
constava/wrapper/__init__.py
constava/wrapper/params.py
constava/wrapper/wrapper.py
constava-1.1.0.dist-info/LICENSE
constava-1.1.0.dist-info/METADATA
constava-1.1.0.dist-info/WHEEL
constava-1.1.0.dist-info/entry_points.txt
constava-1.1.0.dist-info/top_level.txt
constava-1.1.0.dist-info/RECORD
