Metadata-Version: 2.1
Name: constava
Version: 1.1.0
Summary: This software is used to calculate conformational states probability & conformational state variability from a protein structure ensemble.
Home-page: https://bitbucket.org/bio2byte/constava/
Author: Wim Vranken
Author-email: wim.vranken@vub.be
Maintainer: Jose Gavalda-Garcia, David Bickel, Adrian Diaz, Wim Vranken
Maintainer-email: jose.gavalda.garcia@vub.be, david.bickel@vub.be, adrian.diaz@vub.be, wim.vranken@vub.be
License: OSI Approved :: GNU General Public License v3 (GPLv3)
Classifier: Natural Language :: English
Classifier: Programming Language :: Python :: 3.8
Classifier: Programming Language :: Python :: 3.9
Classifier: Programming Language :: Python :: 3.10
Classifier: Programming Language :: Python :: 3.11
Classifier: Programming Language :: Python :: 3.12
Classifier: License :: OSI Approved :: GNU General Public License v3 (GPLv3)
Classifier: Operating System :: OS Independent
Classifier: Topic :: Scientific/Engineering :: Bio-Informatics
Classifier: Topic :: Scientific/Engineering :: Chemistry
Classifier: Topic :: Scientific/Engineering :: Physics
Classifier: Intended Audience :: Science/Research
Classifier: Intended Audience :: Education
Classifier: Development Status :: 5 - Production/Stable
Requires-Python: >=3.8
License-File: LICENSE
Requires-Dist: MDAnalysis
Requires-Dist: numpy
Requires-Dist: pandas
Requires-Dist: scikit-learn
